{
  "sharedDir": "shared",
  "dependenciesDir": "extern",
  "info": {
    "name": "QuestCosmeticLoader",
    "id": "quest-cosmetic-loader",
    "version": "0.2.1",
    "url": "https://github.com/RedBrumbler/QuestCosmeticLoader",
    "additionalData": {
      "branchName": "version-v0.2.1",
      "soLink": "https://github.com/RedBrumbler/QuestCosmeticLoader/releases/download/v0.2.1/libquest-cosmetic-loader_0_2_1.so",
      "debugSoLink": "https://github.com/RedBrumbler/QuestCosmeticLoader/releases/download/v0.2.1/debug_libquest-cosmetic-loader_0_2_1.so"
    }
  },
  "dependencies": [
    {
      "id": "beatsaber-hook",
      "versionRange": "^2.0.0",
      "additionalData": {
        "extraFiles": [
          "src/inline-hook"
        ]
      }
    },
    {
      "id": "zip",
      "versionRange": "*",
      "additionalData": {}
    }
  ],
  "additionalData": {}
}